../../pycdc/tests/inputs/old/25_test_divide_future.pyc (Python 2.5)
[Code]
    File Name: test_divide_future.py
    Object Name: <module>
    Arg Count: 0
    Locals: 0
    Stack Size: 3
    Flags: 0x00002040 (CO_NOFREE | CO_FUTURE_DIVISION)
    [Names]
        '__future__'
        'division'
    [Var Names]
    [Free Vars]
    [Cell Vars]
    [Constants]
        -1
        (
            'division'
        )
        '  1 // 2   ='
        1
        2
        '1.0 // 2.0 ='
        1
        2
        '  1 /  2   ='
        '1.0 /  2.0 ='
        None
        0
        0
        0.5
        0.5
    [Disassembly]
        0       LOAD_CONST              0: -1
        3       LOAD_CONST              1: ('division',)
        6       IMPORT_NAME             0: __future__
        9       IMPORT_FROM             1: division
        12      STORE_NAME              1: division
        15      POP_TOP                 
        16      LOAD_CONST              2: '  1 // 2   ='
        19      PRINT_ITEM              
        20      LOAD_CONST              11: 0
        23      PRINT_ITEM              
        24      PRINT_NEWLINE           
        25      LOAD_CONST              5: '1.0 // 2.0 ='
        28      PRINT_ITEM              
        29      LOAD_CONST              12: 0
        32      PRINT_ITEM              
        33      PRINT_NEWLINE           
        34      LOAD_CONST              8: '  1 /  2   ='
        37      PRINT_ITEM              
        38      LOAD_CONST              13: 0.5
        41      PRINT_ITEM              
        42      PRINT_NEWLINE           
        43      LOAD_CONST              9: '1.0 /  2.0 ='
        46      PRINT_ITEM              
        47      LOAD_CONST              14: 0.5
        50      PRINT_ITEM              
        51      PRINT_NEWLINE           
        52      LOAD_CONST              10: None
        55      RETURN_VALUE            
