../../pycdc/tests/inputs/old/35_matrix_mult_oper.pyc (Python 3.5)
[Code]
    File Name: /home/zrax/dev/cpp/pycdc/build/test.py
    Object Name: <module>
    Arg Count: 0
    Locals: 0
    Stack Size: 3
    Flags: 0x00000040 (CO_NOFREE)
    [Names]
        'm'
    [Var Names]
    [Free Vars]
    [Cell Vars]
    [Constants]
        1
        2
        3
        4
        5
        6
        None
    [Disassembly]
        0       LOAD_CONST              0: 1
        3       LOAD_CONST              1: 2
        6       BUILD_LIST              2
        9       LOAD_CONST              2: 3
        12      LOAD_CONST              3: 4
        15      BUILD_LIST              2
        18      BINARY_MATRIX_MULTIPLY  
        19      STORE_NAME              0: m
        22      LOAD_NAME               0: m
        25      LOAD_CONST              4: 5
        28      LOAD_CONST              5: 6
        31      BUILD_LIST              2
        34      INPLACE_MATRIX_MULTIPLY 
        35      STORE_NAME              0: m
        38      LOAD_CONST              6: None
        41      RETURN_VALUE            
